hookline_sdk/__init__.py
hookline_sdk/decorators.py
hookline_sdk/registry.py
hookline_sdk-0.1.1.dist-info/METADATA
hookline_sdk-0.1.1.dist-info/WHEEL
hookline_sdk-0.1.1.dist-info/top_level.txt
hookline_sdk-0.1.1.dist-info/RECORD
