Metadata-Version: 2.4
Name: hookline-sdk
Version: 0.1.1
Summary: SDK for developing Hookline-compatible plugins with decorators and version registry
Home-page: https://github.com/sommye-ctr/hookline-sdk
Author: Somye Mahajan
Author-email: mahajan.somye@gmail.com
License: MIT
Classifier: Development Status :: 3 - Alpha
Classifier: Intended Audience :: Developers
Classifier: License :: OSI Approved :: MIT License
Classifier: Programming Language :: Python :: 3
Classifier: Programming Language :: Python :: 3.12
Classifier: Topic :: Software Development :: Libraries
Requires-Python: >=3.8
Requires-Dist: packaging>=24.0
